{"categories":[{"name":"Login","videos":[],"faqs":[{"topic":"আমি DIKSHA-তে রেজিস্ট্রী করতে চাই","description":"DIKSHA-তে সাইন আপ করার জন্য:\n<ul>\n<li><a href =\"https://diksha.gov.in/explore\"target=\"_blank\">DIKSHA সম্পর্কে জানুন-এ </a>যান\n<li>আপনি একজন শিক্ষক না শিক্ষার্থী সেটি নির্বাচন করুন</li>\n<li>আপনার অবস্থান সম্পর্কিত বিবরণ আপডেট করুন</li>\n<li>প্রোফাইল আইকনে ক্লিক করুন</li>\n<li><b>লগইনে</b> ক্লিক করুন</li>\n<li>লগইন স্ক্রীনে থাকা </b>এখানে রেজিস্ট্রী করুন-এ</b> ক্লিক করুন</li>\n<li>কিভাবে রেজিস্ট্রী করবেন সে বিষয়ে বিস্তারিত জানতে https://diksha.gov.in/help/getting-started/sign-in/sign-up.html দেখুন</li>\n</ul>\n\n"},{"topic":"আমি আমার রাজ্য পোর্টালের মাধ্যমে DIKHSA-তে লগইন করতে চাই","description":"<p>আপনার স্টেট (রাজ্য) পোর্টাল থেকে DIKSHA-তে লগইন করার জন্য:</p>\n<ul>\n<li><a href=\"https://diksha.gov.in/explore\"> DIKSHA সম্পর্কে জানুন </a>&nbsp-তে যান;</li>\n<li>আপনি যে একজন <strong>শিক্ষক বা শিক্ষিকা</strong> সেটা নির্বাচন করুন</li>\n<li>আপনার অবস্থান&nbsp নির্বাচন করুন;</li>\n<li><strong>প্রোফাইল</strong> আইকনটিতে ক্লিক করুন</li>\n<li><strong>লগইনে</strong> ক্লিক করুন</li>\n<li><strong>স্টেট সিস্টেম সহ লগইন</strong> নির্বাচন করুন</li>\n<li>আপনার স্টেট (রাজ্য) নির্বাচন করুন</li>\n<li>আপনার স্টেট পোর্টালে আপনাকে চালিত করা হবে</li>\n<li>আপনার স্টেটের পক্ষ থেকে আপনাকে দেওয়া <strong>ব্যবহারকারীর নাম</strong> ও <strong>পাসওয়ার্ড</strong> <strong>লগইনে&nbsp এন্টার করুন</li>;</strong>স্ক্রীন&nbsp;</li>\n<li><strong>সাবমিটে</strong> ক্লিক করুন</li>\n<li>স্টেট পোর্টালের মাধ্যমে লগইন করার বিষয়ে আরও বিস্তারিত জানতে, দেখুন&nbsp;<a href=\"https://diksha.gov.in/help/getting-started/login/#logging-in-with-state-system\">সাইন আপ</a></li>\n</ul>\n"}]},{"name":"Profile","videos":[],"faqs":[{"topic":"আমি আমার পাসওয়ার্ড ভুলে গেছি","description":"<p>আপনার পাসওয়ার্ড পুনরায় সেট করতে, এই পদক্ষেপগুলি অনুসরণ করুন এবং আপনার অ্যাকাউন্টটি পুনরুদ্ধার করুন:</p><ul>\nপাসওয়ার্ড ভুলে গেছি-তে</strong></li> <li>ক্লিক করুন <strong>\n<li>DIKSHA-তে <li> রেজিস্ট্রী করার সময় আপনি যে ইমেল অ্যাড্রেস বা মোবাইল নম্বর এবং ব্যবহারকারীর নাম দিয়েছিলেন তা এন্টার করুন\n<li><br></li>\n<li>আপনি আপনার রেজিস্ট্রী করা ইমেল বা মোবাইল নম্বরে একটি ওটিপি পাবেন<li>\n<li><br></li>\n<li> আপনার পাসওয়ার্ডটি পুনরায় সেট করতে এবং আপনার অ্যাকাউন্টটি পুনরুদ্ধার করতে ওটিপি এন্টার করুন </li>\n<li> আপনার পাসওয়ার্ডটি পুনরায় সেট করতে,\n<a href=\"https://diksha.gov.in/help/getting-started/recover-password/index.htmltarget=_blank\">পাসওয়ার্ড পুনরুদ্ধার করুন</a></li></ul>দেখুন"},{"topic":"আমি আমার প্রোফাইল সম্পর্কিত বিবরণ সম্পাদনা করতে চাই","description":"আপনি আপনার প্রোফাইলে নিম্নলিখিত বিবরণগুলি সম্পাদনা করতে পারেন:<ul>\n<li>ব্যক্তিগত বিবরণ যেমন নাম, রাজ্য এবং জেলা </li>\n<li>যোগাযোগের বিবরণ যেমন মোবাইল নম্বর এবং ইমেল অ্যাড্রেস</li>\n<li>অন্যান্য বিবরণ যেমন বোর্ড,মাধ্যমের ভাষা , বিষয় এবং ক্লাস</li>\nপ্রোফাইলের বিবরণ কীভাবে সম্পাদনা করবেন সে সম্পর্কে বিস্তারিত জানতে, দেখুন\n<a href=\"https://diksha.gov.in/help/getting-started/user-profile/index.html\"target=\"_blank\">ব্যবহারকারীর প্রোফাইল</a>"}]},{"name":"Course & certificates","videos":[],"faqs":[{"topic":"আমি আমার শংসাপত্রটি ডাউনলোড করতে চাই","description":"<p>সব কোর্সগুলির ক্ষেত্রে শংসাপত্র দেওয়া হয় না। যদি আপনি কোনও কোর্স সম্পূর্ণ করে থাকেন যেটির ক্ষেত্রে শংসাপত্র দেওয়া হয় সেক্ষেত্রে আপনি আপনার প্রোফাইল পেজে যান, কোর্স নামের.&nbsp পাশে ডাউনলোড চিহ্নটি দেখতে পাবেন;</p>\n<p>যদি আপনি মোবাইল অ্যাপে শংসাপত্রটি ডাউনলোড করতে না পারেন,</p>\n<ul>\n    <li>আপনার কাছে DIKSHA অ্যাপের সাম্প্রতিকতম সংস্করণটি আছে কিনা তা চেক করুন, যদি না থাকে, Play store থেকে অ্যাপ সংস্করণটি আপডেট করুন</li>\n    <li><strong>কোর্স অ্যাটেনডেড</strong> বিভাগে <strong>প্রোফাইল</strong> ট্যাবের মধ্যে রিফ্রেশ বোতামটিতে ক্লিক করুন </li>\n    <li>যদি এখনও আপনি শংসাপত্রটি ডাউনলোড করতে না পারেন তবে আমাদের লিখে পাঠান এখানে:\n<ul>\n            <li style=\"margin-left: 20px;\">কোর্সটির নাম</li>\n            <li style=\"margin-left: 20px;\">আপনার DIKSHA আইডি</li>\n            <li style=\"margin-left: 20px;\">প্রোফাইল পেজের যেখানে কোর্সের বিস্তারিত বিবরণ দেখানো হয়েছে সেই অংশটির স্ক্রীনশট</li>\n        </ul>\n    </li>\n</ul>\n"},{"topic":"আমি একটি কোর্সে যোগ দিতে চাই","description":"<p>কোনও কোর্সের জন্য নাম নথিভুক্ত করতে আপনাকে অবশ্যই DIKSHA.&nbsp-তে লগইন করতে হবে;<p>\n<p><strong>কোর্স</strong> বিভাগে নেভিগেট করুন ও নির্দিষ্ট কোর্সটির সন্ধান করুন। কোনও কোর্সে যোগদান করার জন্য বিস্তারিতভাবে জানতে ও কোনও ব্যাচে নাম নথিভুক্ত করতে, দেখুন <p>\n<ul>\n<li><a href=\"https://diksha.gov.in/help/getting-started/diksha-mobile-app/course.html\" target=\"_blank\">কোর্স</a></li>\n<li><a href=\"https://diksha.gov.in/help/getting-started/diksha-mobile-app/enrolling-course.html\" target=\"_blank\">একটি কোর্সে যোগদান করুন</a></li>\n</ul>"},{"topic":"আমার কোর্স সম্পূর্ণ করার পর আমি আমার শংসাপত্রটি দ্রুত পেতে চাই","description":"কোনও রাজ্যের কর্তৃপক্ষ কোর্সটির শংসাপত্র কখন প্রস্তুত করা হবে সে বিষয়ে সিদ্ধান্ত নেয়। কিছু কোর্সে শংসাপত্র কোর্সটি শেষ হবার 7 দিনের মধ্যে প্রস্তুত করা হয়। কিন্তু, কিছু কোর্সের শংসাপত্র প্রস্তুত করা হবে কোর্সটির ব্যাচের সময়কাল সম্পূর্ণ হবার পরে। কখন আপনার কোর্সটির শংসাপত্র প্রস্তুত করা হবে তা জানতে আপনার রাজ্য বা কোর্সের প্রশাসকের সাথে যোগাযোগ করুন। আপনার শংসাপত্রটি প্রস্তুত হবার পর যত তাড়াতাড়ি সম্ভব আপনাকে বিজ্ঞপ্তি পাঠিয়ে জানানো হবে।"},{"topic":"আমার কোর্স কতটা সম্পূর্ণ হয়েছে তা আমি পরীক্ষা করতে চাই","description":"আপনার কোর্স কতটা (in %) সম্পূর্ণ হয়েছে সেটি আপনার কোর্স পেজের উপরে ডানদিকে দেখানো হয়েছে।"},{"topic":"কোনও কোর্সের শেষে শংসাপত্র দেওয়া হবে কিনা আমি সে বিষয়ে নিশ্চিত হতে চাই","description":"কোর্স কার্ডের পৃষ্ঠাটি নির্দেশ করে যে কোর্সটির ক্ষেত্রে কোনও শংসাপত্র দেওয়া হয় কিনা।  একটি বার্তা কোর্সের বিশদ বিবরণযুক্ত স্ক্রীনে দেখানো হয় যেখানে উল্লেখ করা থাকে যে </b>এই কোর্সটির শেষে শংসাপত্র দেওয়া হয়<b>।"},{"topic":"আমার শংসাপত্র প্রস্তুত হবার পর আমি একটি বিজ্ঞপ্তির মাধ্যমে তা জানতে চাই","description":"শংসাপত্রটি প্রস্তুত হওয়ার পরে আপনার রেজিস্ট্রী করা ইমেল অ্যাড্রেস বা ফোন নম্বরে বিজ্ঞপ্তি পাঠিয়ে আপনাকে জানানো হবে।"},{"topic":"আমাকে যে শংসাপত্র দেওয়া হয়েছে তাতে আমি নিজের নামটি পরিবর্তন করতে চাই","description":"আপনার শংসাপত্রে আপনার সেই নামটি ব্যবহার করা হয়েছে যেটি আপনার প্রোফাইল পেজে আছে। আপনার প্রোফাইল পেজে থাকা নামটি সংশোধন করুন ও আপনার রাজ্য কর্তৃপক্ষের সাথে যোগাযোগ করুন। রাজ্য কর্তৃপক্ষের কাছে আবেদন করুন যাতে তারা প্রয়োজনীয় বিবরণসহ একটি পরিষেবা অনুরোধ DIKSHA সহায়তাকারী দলের কাছে পাঠায় আপনার শংসাপত্রটি পুনরায় প্রস্তুত করার জন্য। অনুরোধটি পাবার পর শংসাপত্রটি পুনরায় প্রস্তুত করতে আনুমানিক 24 ঘন্টা বা একটি কর্মদিবস সময় লাগবে।"},{"topic":"আমি আমার কোর্সটি সম্পূর্ণ করেছি, কিন্তু কোর্সটি 100% সম্পূর্ণ হিসেবে দেখানো হচ্ছে না","description":"প্রক্রিয়া সংক্রান্ত আপডেটটি সিঙ্ক করতে সিস্টেমের কয়েক ঘন্টা সময় লাগতে পারে, সুতরাং, আপনি যে কোর্সটি সম্পূর্ণ করেছেন তা দেরিতে দেখানো হতে পারে।  আপনাকে একদিন পর চেক করার অনুরোধ করা হচ্ছে।"},{"topic":"DIKSHA-তে আমি  কিছু প্রয়োজনীয় বিষয়বস্তু যোগ করতে চাই","description":"DIKSHA-তে শিক্ষামূলক বিষয়বস্তু দান করার জন্য, <a href=\"https://vdn.diksha.gov.in/\"target=_\"blank\">বিদ্যাদান পোর্টাল</a>-এ যান"},{"topic":"আমি আমার কোর্সটি খুঁজে পাচ্ছি না","description":"আপনার কোর্সটি অনুসন্ধান করতে, <b>Courses</b> বিভাগে নেভিগেট করুন।  অনুসন্ধানের ফলাফলগুলি সংক্ষিপ্ত করতে কোর্স ফিল্টারগুলি ব্যবহার করুন বা অনুসন্ধান বারে কোর্সের নামটি টাইপ করুন এবং এন্টার বোতামটি টিপুন।"},{"topic":"আমার প্রোফাইলটি আমার কোর্সের অগ্রগতিটি সঠিকভাবে প্রতিফলিত করে না","description":"আপনার প্রোফাইলে আপনার কোর্সের অগ্রগতি আপডেট করতে, <b>আমার শিক্ষণগুলিতে </b> যান। কোর্সে ক্লিক করুন । কোর্স উন্মুক্ত হওয়ার পর, কেবাব মেনুতে যান (ডানদিকে তিনটি উল্লম্ব বিন্দু রয়েছে) > ক্লিক করুন <b>এখন সিঙ্ক অগ্রগতি হচ্ছে </b> ক্লিক করুন। কয়েক মিনিট অপেক্ষা করুন। আপনার প্রোফাইলে এখন আপনার সঠিক কোর্সের অগ্রগতি প্রতিফলিত হওয়া  উচিত।"}]}],"constants":{"charactersLeft":"অক্ষর বাকি","explainMsg":"আপনি কি সমস্যা  টি ব্যাখ্যা করতে পারবেন?","faqMsg":"সচরাচর জিজ্ঞাস্য","faqTitle":"সচরাচর জিজ্ঞাস্য করা প্রশ্ন( গুলি) ","help":"সাহায্য ","helpMsg":"এই উত্তরটি  আপনাকে সাহায্য করেছিল?","initiateEmailButton":"ইমেইল পাঠান\n","knowMoreMsg":"আপনি  আর কি  জানতে চান?","noMsg":"না","reportIssue":"সমস্যা  রিপোর্ট করুন","reportIssueMsg":"অন্যান্য সমস্যা গুলি রিপোর্ট করুন","resolveMsg":"বিষয়বস্তু, প্রযুক্তিগত বিষয়বস্তু এবং আরও অনেক কিছু সন্ধানে সহায়তা পান। এফএকিউ, সহায়তা ভিডিও এবং আরও অনেক কিছুর জন্য বিষয়গুলির মাধ্যমে ব্রাউজ করুন।","selectCategoryTitle":"বিভাগ নির্বাচন করুন","sorryMsg":"এর জন্যে দুঃখিত!","submitButton":"প্রতিক্রিয়া জমা দিন","tellMoreMsg":"আপনি  যে সমস্যার  সম্মুখীন হয়েছেন তার সম্পর্কে আমাদের আরো বলুন","thanksForFeedbackMsg":"আপনার প্রতিক্রিয়ার জন্য ধন্যবাদ। আমরা আমাদের কাছে পাঠানো প্রতিটি পরামর্শের জবাব দিতে সক্ষম নাও হতে পারি, তবে আপনার প্রতিক্রিয়া মূল্যবান। এটি তৈরি করতে সহায়তা করে {{app_name}} সবার জন্য ভাল।","thanksMsg":"আপনার প্রতিক্রিয়ার জন্য ধন্যবাদ!","triggerEmailMsg":"আপনি টেক্সট বাক্সে বিশদ যুক্ত করার পরে, ইনিশিয়েটিভ ইমেল বোতামটি  তে ক্লিক করুন, আমরা আপনার হয়ে একটি ইমেল ট্রিগার করব। আপনি আরও বিস্তারিত যোগ করতে পারেন এবং/ অথবা সংযুক্ত ফাইল যোগ করতে পারেন","typeHere":"এখানে লিখুন...","videoTitle":"ভিডিও(গুলি)","yesMsg":"হ্যাঁ "}}