{"faqs":[{"topic":"ਮੈਂ ਆਪਣਾ ਬੋਰਡ, ਮਾਧਿਅਮ, ਕਲਾਸ ਅਤੇ ਵਿਸ਼ਾ ਨਹੀਂ ਦੇਖ ਸਕਦਾ","description":"ਤੁਹਾਡਾ ਰਾਜ ਇਸ ਸਮੇਂ ਸਾਰੇ ਬੋਰਡਾਂ, ਮਾਧਿਅਮ, ਕਲਾਸਾਂ ਅਤੇ ਵਿਸ਼ਿਆਂ ਦਾ ਸਮਰਥਨ ਨਹੀਂ ਕਰਦਾ। ਜਿਉਂ ਹੀ ਤੁਹਾਡਾ ਰਾਜ ਉਹਨਾਂ ਨੂੰ ਸ਼ਾਮਲ ਕਰੇਗਾ, ਤੁਸੀਂ ਇਸਨੂੰ ਸੂਚੀ ਵਿੱਚ ਵੇਖੋਗੇ"},{"topic":"ਮੈਂ ਕੰਟੇਂਟ ਡਾਊਨਲੋਡ ਕੀਤੇ ਹਨ, ਪਰ ਮੈਂ ਇਸਨੂੰ ਚਲਾਉਣ ਵਿੱਚ ਅਸਮਰੱਥ ਹਾਂ ਕਿਉਂਕਿ ਇਹ ਕਹਿੰਦਾ ਹੈ ਕਿ ਮੈਨੂੰ ਇੰਟਰਨੈੱਟ ਦੀ ਜ਼ਰੂਰਤ ਹੈ","description":"ਤੁਸੀਂ YouTube ਕੰਟੇਂਟ ਨੂੰ ਡਾਊਨਲੋਡ ਕੀਤਾ ਹੋ ਸਕਦਾ ਹੈ। ਤੁਸੀਂ ਉਦੋਂ ਹੀ YouTube ਕੰਟੇਂਟ ਨੂੰ ਚਲਾ ਸਕਦੇ ਹੋ ਜਦੋਂ ਤੁਸੀਂ ਆਨਲਾਈਨ ਹੋ। ਕੰਪਿਊਟਰ ਨੂੰ ਇੰਟਰਨੈੱਟ ਨਾਲ ਕਨੈਕਟ ਕਰੋ ਦੁਬਾਰਾ ਕੋਸ਼ਿਸ਼ ਕਰੋ।"},{"topic":"ਮੈਨੂੰ ਆਪਣੀ SUNBIRD ਡੈਸਕਟਾਪ ਐਪ ਨੂੰ ਅਪਡੇਟ ਕਰਨ ਦੀ ਜ਼ਰੂਰਤ ਹੈ","description":"ਆਪਣੇ ਕੰਪਿਊਟਰ ਨੂੰ ਇੰਟਰਨੈੱਟ ਨਾਲ ਕਨੈਕਟ ਕਰੋ ਅਤੇ ਨਵੀਨਤਮ ਐਪ ਸੰਸਕਰਣ ਲਈ <a href=\"https://staging.sunbirded.org/download/desktopapp\" target=\"_blank\">https://staging.sunbirded.org/download/desktopapp</a> ਚੈੱਕ ਕਰੋ"},{"topic":"ਮੇਰੇ ਕੋਲ ਇੰਟਰਨੈਟ ਕਨੈਕਸ਼ਨ ਵਾਲੇ ਲੈਪਟਾਪ ਤੱਕ ਐਕਸੈਸ ਨਹੀਂ ਹੈ, ਪਰ ਮੈਂ ਡੈਸਕਟੌਪ ਐਪ 'ਤੇ ਕੰਟੇਂਟ ਨੂੰ ਸ਼ਾਮਲ ਕਰਨਾ ਜਾਂ ਅਪਡੇਟ ਕਰਨਾ ਚਾਹੁੰਦਾ ਹਾਂ","description":"ਜੇ ਤੁਹਾਡੇ ਕੋਲ ਮੋਬਾਈਲ ਫ਼ੋਨ ਹੈ, SUNBIRD ਮੋਬਾਈਲ ਐਪ ਨੂੰ ਗੂਗਲ ਪਲੇਸਟੋਰ ਤੋਂ ਡਾਊਨਲੋਡ ਕਰੋ।\nਐਪ ਵਿਚਲੇ ਕੰਟੇਂਟ ਲਈ ਬਰਾਊਜ਼ ਕਰੋ।\nSUNBIRD ਲਾਇਬ੍ਰੇਰੀ ਤੋਂ ਕੰਟੇਂਟ ਡਾਊਨਲੋਡ ਕਰੋ।\nਇਸਨੂੰ ਪੈੱਨਡਰਾਈਵ ਜਾਂ SD ਕਾਰਡ 'ਤੇ ਕਾਪੀ ਕਰੋ ਅਤੇ ਇਸਨੂੰ SUNBIRD ਐਪ 'ਤੇ ਅਪਲੋਡ ਕਰੋ।"},{"topic":"ਮੈਨੂੰ ਕਿਸੇ ਖ਼ਾਸ ਵਿਸ਼ੇ ਲਈ ਕੰਟੇਂਟ ਨਹੀਂ ਮਿਲਦੇ, ਜਾਂ ਅਢੁੱਕਵੇਂ ਕੰਟੇਂਟ ਮਿਲਦੇ ਹਨ","description":"ਕੰਟੇਂਟ ਦੀ ਭਾਲ ਕਰਨ ਲਈ SUNBIRD ਦੀ ਆਨਲਾਈਨ ਲਾਇਬ੍ਰੇਰੀ ਨੂੰ ਬਰਾਊਜ਼ ਕਰੋ। ਜੇ ਇਹ ਅਜੇ ਵੀ ਉਪਲੱਬਧ ਨਹੀਂ ਹੈ, ਤਾਂ ਕੰਟੇਂਟ ਬਾਰੇ ਆਪਣੀ ਫੀਡਬੈਕ ਸਟੇਟ SCERT ਨੂੰ ਭੇਜੋ"},{"topic":"ਐਪ ਬਹੁਤ ਹੌਲੀ ਹੈ","description":"ਐਪ ਦੀ ਕਾਰਗੁਜ਼ਾਰੀ ਨੂੰ ਤੇਜ਼ ਕਰਨ ਲਈ, ਇਹ ਕਰੋ:\n<br>ਆਪਣੇ ਕੰਪਿਊਟਰ ਦੀ ਸਿਸਟਮ ਕੌਨਫਿਗਰੇਸ਼ਨ 'ਤੇ ਜਾਓ। ਘੱਟੋ ਘੱਟ ਕੌਂਫਿਗਰੇਸ਼ਨ ਹੋਣੀ ਚਾਹੀਦੀ ਹੈ:\n<ul><li>2 GB RAM</li>\n<li>Dual Core Processor</li></ul>\n<br>ਜੇ ਤੁਹਾਡਾ ਕੰਪਿਊਟਰ ਇਸ ਕੌਂਫਿਗਰੇਸ਼ਨ ਨਾਲ ਮੇਲ ਖਾਂਦਾ ਜਾਂ ਵੱਧ ਹੈ, ਤਾਂ ਐਪ ਨੂੰ ਮੁੜ ਚਾਲੂ ਕਰੋ।\n<br>ਅਜਿਹਾ ਕਰਨ ਤੋਂ ਬਾਅਦ, ਜੇ ਇਹ ਅਜੇ ਵੀ ਹੌਲੀ ਹੈ, <b>ਟਾਸਕ ਮੈਨੇਜਰ</b> 'ਤੇ ਜਾਓ,\nਸਾਰੀਆਂ ਨਾ ਵਰਤੀਆਂ ਬੈਕਗਰਾਂਊਡ ਪ੍ਰਕਿਰਿਆਵਾਂ ਨੂੰ ਚੁਣੋ ਅਤੇ ਕਲਿੱਕ ਕਰੋ<b>End Task</b>"},{"topic":"ਮੈਂ ਪੈੱਨਡਰਾਈਵ ਵਿੱਚ ਕੰਟੇਂਟ ਦੀ ਨਕਲ ਕਰਨ ਵਿੱਚ ਅਸਮਰੱਥ ਹਾਂ","description":"ਪੈੱਨਡਰਾਈਵ 'ਤੇ ਕੰਟੇਂਟ ਦੀ ਨਕਲ ਕਰਨ ਲਈ, ਇਹ ਕਰੋ:\n<ul><li>ਆਪਣੀ ਕੰਪਿਊਟਰ ਸੈਟਿੰਗਸ 'ਤੇ ਜਾਓ। ਜਾਂਚ ਕਰੋ ਕਿ ਕੀ USB ਡਰਾਈਵ ਲਿਖਣ ਤੋਂ ਸੁਰੱਖਿਅਤ ਹੈ। ਜੇ ਇਹ ਹੈ, ਤਾਂ ਸੁਰੱਖਿਆ ਨੂੰ ਅਯੋਗ ਕਰੋ</li>\n<li>ਜਾਂਚ ਕਰੋ ਕਿ ਕੀ ਪੈੱਨਡਰਾਈਵ ਵਿੱਚ ਖ਼ਾਲੀ ਥਾਂ ਹੈ। ਆਪਣੀ ਪੈੱਨਡਰਾਈਵ ਤੋਂ ਅਣਚਾਹੀਆਂ ਫਾਈਲਾਂ ਨੂੰ ਡੀਲੀਟ ਕਰੋ</li></ul>\n"},{"topic":"ਮੈਂ ਆਪਣੀ ਪੇਨਡਰਾਈਵ 'ਤੇ ਕੰਟੇਂਟ ਲੋਡ ਕੀਤੇ ਸਨ, ਪਰ ਹੁਣ ਮੈਂ ਵੇਖਦਾ ਹਾਂ ਕਿ ਇਹ ਖ਼ਾਲੀ ਹੈ","description":"ਤੁਹਾਡੀ ਪੇਨਡਰਾਈਵ ਜਾਂ ਕੰਪਿਊਟਰ ਕਿਸੇ ਵਾਇਰਸ ਨਾਲ ਸੰਕਰਮਿਤ ਹੋ ਸਕਦਾ ਹੈ। ਇਹ ਵੇਖੋ ਕਿ:\n<ul>\n<li>ਤੁਹਾਡੀ ਮਸ਼ੀਨ 'ਤੇ ਇਕ ਐਂਟੀ ਵਾਇਰਸ ਸਾਫਟਵੇਅਰ ਸਥਾਪਤ ਹੈ</li>\n<li>ਤੁਹਾਡੀ ਪੇਨਡਰਾਈਵ ਨੂੰ ਅਣਜਾਣ ਮਸ਼ੀਨਾਂ ਵਿਚ ਲਗਾਉਣ ਤੋਂ ਪਹਿਲਾਂ ਲਿਖਤ-ਸੁਰੱਖਿਅਤ ਕੀਤਾ ਗਿਆ ਹੈ</li>\n</ul>"},{"topic":"ਮੇਰੀ ਪੇਨਡਰਾਈਵ 'ਤੇ ਅਤੇ ਪੇਨਡਰਾਈਵ ਤੋਂ ਕੰਟੇਂਟ ਦੀ ਨਕਲ ਕਰਨ ਲਈ ਸਮਾਂ ਲਗਦਾ ਹੈ","description":"ਕਾਪੀ ਕਰਨ ਲਈ ਲਿਆ ਗਿਆ ਸਮਾਂ ਕੰਟੇਂਟ ਫਾਈਲ ਦੇ ਅਕਾਰ 'ਤੇ ਨਿਰਭਰ ਕਰਦਾ ਹੈ। ਕੁਝ ਵੱਡੀਆਂ ਪਾਠ-ਪੁਸਤਕਾਂ ਦੀ ਨਕਲ ਕਰਨ ਲਈ ਸਮਾਂ ਲੱਗਦਾ ਹੈ। ਅਸੀਂ ਤੁਹਾਨੂੰ ਸਿਫਾਰਸ਼ ਕਰਦੇ ਹਾਂ ਕਿ ਤੁਸੀਂ ਪ੍ਰਕਿਰਿਆ ਨੂੰ ਵਿਚਕਾਰ ਨਾ ਰੋਕੋ। ਅਜਿਹਾ ਕਰਨ ਨਾਲ ਅਸੰਗਤ ਫਾਈਲਾਂ ਲੱਗ ਸਕਦੀਆਂ ਹਨ।"},{"topic":"ਮੇਰੇ ਕੰਪਿਊਟਰ ਵਿੱਚ SUNBIRD ਕੰਟੇਂਟ ਕਾਰਨ ਕੋਈ ਖ਼ਾਲੀ ਥਾਂ ਨਹੀਂ ਹੈ","description":"ਆਪਣੇ ਕੰਪਿਊਟਰ 'ਤੇ ਜਗ੍ਹਾ ਖ਼ਾਲੀ ਕਰਨ ਲਈ ਐਪ ਦੀ ਮਾਈ ਡਾਊਨਲੋਡਸ ਟੈਬ ਤੋਂ ਡਾਊਨਲੋਡ ਕੀਤੇ ਕੰਟੇਂਟ ਨੂੰ ਡੀਲੀਟ ਕਰੋ"},{"topic":"ਮੇਰੇ ਉਬੰਤੂ ਸਿਸਟਮ 'ਤੇ SUNBIRD ਡੈਸਕਟਾਪ ਐਪਲੀਕੇਸ਼ਨ ਸਥਾਪਤ ਕਰਨ ਵਿੱਚ ਅਸਮਰੱਥ","description":"<p>ਆਪਣੇ ਉਬੰਤੂ ਸਿਸਟਮ 'ਤੇ SUNBIRD ਡੈਸਕਟਾਪ ਐਪਲੀਕੇਸ਼ਨ ਨੂੰ ਸਥਾਪਤ ਕਰਨ ਲਈ:</p>\n<p>1) ਆਪਣਾ ਟਰਮੀਨਲ ਖੋਲ੍ਹੋ</p>\n<p>2) ਡਾਇਰੈਕਟਰੀ ਨੂੰ ਤਬਦੀਲ ਕਰਨ ਲਈ ਸੀਡੀ <ਲੋਕੇਸ਼ਨ> ਕਮਾਂਡ ਚਲਾਓ, ਜਿੱਥੇ deb ਫਾਈਲ ਡਾਊਨਲੋਡ ਕੀਤੀ ਗਈ ਹੈ। ਉਦਾਹਰਣ ਲਈ, ਜੇ deb ਨੂੰ ਡਾਊਨਲੋਡਸ ਫੋਲਡਰ ਵਿੱਚ ਸੇਵ ਕੀਤਾ ਗਿਆ ਹੈ, ਤਾਂ ਸੀਡੀ ਡਾਊਨਲੋਡਸ ਕਮਾਂਡ ਚਲਾਓ</p>\n<p>3) sudo dpkg -i <ਫਾਈਲ ਦਾ ਨਾਮ>ਕਮਾਂਡ ਚਲਾਓ </p>\n<p>ਇਸ ਕਮਾਂਡ ਨੂੰ ਸਫ਼ਲਤਾਪੂਰਵਕ ਚਲਾਉਣ 'ਤੇ ਐਪਲੀਕੇਸ਼ਨ ਲਾਂਚ ਹੋ ਜਾਂਦੀ ਹੈ </p>"},{"topic":"ਮੈਂ SUNBIRD 'ਤੇ ਰਜਿਸਟਰ ਹੋਣਾ ਚਾਹੁੰਦਾ ਹਾਂ","description":"SUNBIRD: ’ਤੇ ਰਜਿਸਟਰ ਕਰਨ ਲਈ: \n<ul>\n <li> <a href =\"https://staging.sunbirded.org/explore\" target=\"_blank\">SUNBIRD 'ਤੇ ਪੜਚੋਲ ਕਰੋ </a> 'ਤੇ ਜਾਓ </li>\n<li>ਚੁਣੋ ਕਿ ਕੀ ਤੁਸੀਂ ਅਧਿਆਪਕ ਹੋ ਜਾਂ ਵਿਦਿਆਰਥੀ</li>\n<li>ਆਪਣੇ ਸਥਾਨ ਦੇ ਵੇਰਵਿਆਂ ਨੂੰ ਅਪਡੇਟ ਕਰੋ</li>\n<li>ਪ੍ਰੋਫਾਈਲ ਆਈਕਾਨ 'ਤੇ ਕਲਿੱਕ ਕਰੋ</li>\n<li> <b>ਲੌਗਿਨ</b>'ਤੇ ਕਲਿਕ ਕਰੋ </li>\n<li> ਲੌਗਿਨ ਸਕ੍ਰੀਨ 'ਤੇ <b>ਇੱਥੇ ਰਜਿਸਟਰ ਕਰੋ</b> 'ਤੇ ਕਲਿਕ ਕਰੋ </li>\n<li> ਰਜਿਸਟਰ ਕਿਵੇਂ ਕਰੀਏ ਬਾਰੇ ਜਾਣਕਾਰੀ ਲਈ <a href=\"https://staging.sunbirded.org/help/getting-started/sign-in/sign-up.html\" target=\"_blank\">https://staging.sunbirded.org/help/getting-started/sign-in/sign-up.html</a> ਵੇਖੋ</li>\n</ul>"},{"topic":"ਮੈਂ ਆਪਣਾ ਪਾਸਵਰਡ ਭੁੱਲ ਗਿਆ ਹਾਂ","description":"<p>ਆਪਣਾ ਪਾਸਵਰਡ ਰੀਸੈੱਟ ਕਰਨ ਲਈ, ਇਨ੍ਹਾਂ ਕਦਮਾਂ ਦੀ ਪਾਲਣਾ ਕਰੋ ਅਤੇ ਆਪਣੇ ਖਾਤੇ ਨੂੰ ਮੁੜ ਪ੍ਰਾਪਤ ਕਰੋ:</p>\n<ul>\n<li> <strong>ਪਾਸਵਰਡ ਭੁੱਲ ਗਏ </strong> 'ਤੇ ਕਲਿਕ ਕਰੋ</li>\n<li>ਉਹ ਈਮੇਲ ਪਤਾ ਜਾਂ ਮੋਬਾਈਲ ਨੰਬਰ ਅਤੇ ਉਪਭੋਗਤਾ ਦਾ ਨਾਮ ਦਰਜ ਕਰੋ ਜੋ ਤੁਸੀਂ SUNBIRD 'ਤੇ ਰਜਿਸਟਰ ਕਰਨ ਵੇਲੇ ਪ੍ਰਦਾਨ ਕੀਤਾ ਸੀ</li>\n<li>ਤੁਸੀਂ ਆਪਣੀ ਰਜਿਸਟਰਡ ਈਮੇਲ ਜਾਂ ਮੋਬਾਈਲ ਨੰਬਰ 'ਤੇ ਇਕ OTP ਪ੍ਰਾਪਤ ਕਰੋਗੇ</li><li>ਆਪਣਾ ਪਾਸਵਰਡ ਰੀਸੈੱਟ ਕਰਨ ਅਤੇ ਆਪਣੇ ਖਾਤੇ ਨੂੰ ਮੁੜ ਪ੍ਰਾਪਤ ਕਰਨ ਲਈ OTP ਦਰਜ ਕਰੋ</li>\n<li>ਆਪਣੇ ਪਾਸਵਰਡ ਨੂੰ ਰੀਸੈੱਟ ਕਰਨ ਲਈ ਵੇਰਵਿਆਂ ਲਈ, ਵੇਖੋ <a href=\"https://staging.sunbirded.org/help/getting-started/recover-password/index.html\" target=\"_blank\">ਪਾਸਵਰਡ ਮੁੜ ਪ੍ਰਾਪਤ ਕਰੋ</a></li>\n</ul>"},{"topic":"ਮੈਂ ਆਪਣੇ ਰਾਜ ਪੋਰਟਲ ਦੁਆਰਾ SUNBIRD 'ਤੇ ਲੌਗਇਨ ਕਰਨਾ ਚਾਹੁੰਦਾ ਹਾਂ","description":"<p>ਆਪਣੇ ਸਟੇਟ ਪੋਰਟਲ ਰਾਹੀਂ SUNBIRD ਵਿੱਚ ਲੌਗਇਨ ਕਰਨ ਲਈ:</p>\n<ul>\n  <li><a href=\"https://staging.sunbirded.org/explore\" target=\"_blank\">SUNBIRD ਦੀ ਪੜਚੋਲ ਕਰੋ 'ਤੇ ਜਾਓ</a>&nbsp;</li>\n  <li>ਚੁਣੋ ਕਿ ਤੁਸੀਂ ਇੱਕ <strong>ਅਧਿਆਪਕ</strong> ਹੋ </li>\n  <li>ਆਪਣਾ ਟਿਕਾਣਾ&nbsp; ਚੁਣੋ</li>\n  <li><strong>ਪ੍ਰੋਫਾਈਲ</strong> ਆਈਕਾਨ 'ਤੇ ਕਲਿਕ ਕਰੋ</li>\n  <li><strong>ਲੌਗਇਨ</strong> 'ਤੇ ਕਲਿਕ ਕਰੋ</li>\n  <li><strong>ਸਟੇਟ ਸਿਸਟਮ ਨਾਲ ਲੌਗਇਨ ਕਰੋ</strong> ਦੀ ਚੋਣ ਕਰੋ</li>\n  <li>ਆਪਣੇ ਰਾਜ ਦੀ ਚੋਣ ਕਰੋ</li>\n  <li>ਤੁਹਾਨੂੰ ਤੁਹਾਡੇ ਸਟੇਟ ਪੋਰਟਲ 'ਤੇ ਭੇਜਿਆ ਜਾਵੇਗਾ</li>\n  <li>ਤੁਹਾਡੇ ਰਾਜ ਦੁਆਰਾ ਤੁਹਾਨੂੰ ਦਿੱਤਾ ਗਿਆ<strong> ਉਪਭੋਗਤਾ ਦਾ ਨਾਮ</strong> ਅਤੇ<strong> ਪਾਸਵਰਡ</strong> <strong>ਲੌਗਇਨ&nbsp;</strong> ਸਕ੍ਰੀਨ&nbsp; ਵਿੱਚ ਦਾਖਲ ਕਰੋ</li>\n  <li><strong>ਜਮ੍ਹਾਂ ਕਰੋ</strong> 'ਤੇ ਕਲਿਕ ਕਰੋ</li>\n  <li>ਸਟੇਟ ਪੋਰਟਲ ਰਾਹੀਂ ਲੌਗਇਨ ਕਰਨ ਬਾਰੇ ਜਾਣਕਾਰੀ ਲਈ, ਵੇਖੋ&nbsp;<a\n      href=\"https://staging.sunbirded.org/help/getting-started/login/#logging-in-with-state-system\" target=\"_blank\">ਸਾਇਨ ਅਪ</a></li>\n</ul>"},{"topic":"ਮੈਂ ਆਪਣੇ ਪ੍ਰੋਫਾਈਲ ਵੇਰਵਿਆਂ ਦੀ ਸੋਧ ਕਰਨਾ ਚਾਹੁੰਦਾ ਹਾਂ","description":"ਤੁਸੀਂ ਆਪਣੇ ਪ੍ਰੋਫਾਈਲ ਵਿਚ ਹੇਠ ਦਿੱਤੇ ਵੇਰਵਿਆਂ ਨੂੰ ਸੋਧ ਸਕਦੇ ਹੋ:\n<ul>\n  <li>ਨਿੱਜੀ ਵੇਰਵੇ ਜਿਵੇਂ ਨਾਮ, ਰਾਜ ਅਤੇ ਜ਼ਿਲ੍ਹਾ</li>\n  <li>ਸੰਪਰਕ ਵੇਰਵੇ ਜਿਵੇਂ ਮੋਬਾਈਲ ਨੰਬਰ ਅਤੇ ਈਮੇਲ ਪਤਾ</li>\n  <li>ਹੋਰ ਵੇਰਵੇ ਜਿਵੇਂ ਬੋਰਡ, ਮਾਧਿਅਮ, ਵਿਸ਼ਾ, ਅਤੇ ਕਲਾਸ</li>\n  ਪ੍ਰੋਫਾਈਲ ਵੇਰਵਿਆਂ ਵਿੱਚ ਕਿਵੇਂ ਸੋਧ ਕਰਨੀ ਹੈ ਬਾਰੇ ਜਾਣਕਾਰੀ ਲਈ, ਵੇਖੋ<a href=\"https://staging.sunbirded.org/help/getting-started/user-profile/index.html\" target=\"_blank\">ਉਪਭੋਗਤਾ ਪ੍ਰੋਫਾਈਲ</a>\n</ul>"},{"topic":"ਜਦੋਂ ਮੈਂ ਆਫ਼ਲਾਈਨ ਹੁੰਦਾ ਹਾਂ ਤਾਂ ਮੈਂ ਕੋਰਸਾਂ ਤੱਕ ਨਹੀਂ ਪਹੁੰਚ ਸਕਦਾ","description":"ਕੋਰਸ ਕੇਵਲ ਤਾਂ ਹੀ ਉਪਲੱਬਧ ਹੁੰਦੇ ਹਨ ਜਦੋਂ ਤੁਸੀਂ ਇੰਟਰਨੈੱਟ ਨਾਲ ਜੁੜੇ ਹੁੰਦੇ ਹੋ"}],"constants":{"charactersLeft":"ਅੱਖਰ ਬਚੇ","explainMsg":"ਕੀ ਤੁਸੀਂ ਸਮੱਸਿਆ ਬਾਰੇ ਦੱਸ ਸਕਦੇ ਹੋ?","faqMsg":"ਅਕਸਰ ਪੁੱਛੇ ਜਾਣ ਵਾਲੇ ਸਵਾਲ","help":"ਮਦਦ ","helpMsg":"ਕੀ ਇਸ ਜਵਾਬ ਨੇ ਤੁਹਾਡੀ ਮਦਦ ਕੀਤੀ?","initiateEmailButton":"ਈਮੇਲ ਅਰੰਭ ਕਰੋ","knowMoreMsg":"ਤੁਸੀਂ ਹੋਰ ਕੀ ਜਾਣਨਾ ਚਾਹੋਗੇ?","noMsg":"ਨਹੀਂ","reportIssue":" ਮੁੱਦੇ ਦੀ ਰਿਪੋਰਟ ਕਰੋ","reportIssueMsg":"ਹੋਰ ਮੁੱਦੇ ਦੀ ਰਿਪੋਰਟ ਕਰੋ","resolveMsg":"ਆਪਣੇ ਮੁੱਦੇ ਨੂੰ ਸੁਲਝਾਉਣ ਲਈ ਸੂਚੀ ਨੂੰ ਵੇਖੋ","sorryMsg":"ਉਸ ਲਈ ਮੈ ਅਫ਼ਸੋਸ ਕਰਦਾਂ!","submitButton":"ਜਮ੍ਹਾ ਕਰੋ","tellMoreMsg":"ਆਪਣੀਆ ਸਮੱਸਿਆ ਦੇ ਬਾਰੇ ਸਾਨੂੰ ਹੋਰ ਦੱਸੋ","thanksMsg":"ਤੁਹਾਡੇ ਜਵਾਬ ਲਈ ਧੰਨਵਾਦ!","triggerEmailMsg":"ਟੈਕਸਟ ਬਾਕਸ ਵਿੱਚ ਵੇਰਵੇ ਸ਼ਾਮਲ ਕਰਨ ਅਤੇ ਈਮੇਲ ਅਰੰਭ ਬਟਨ ਨੂੰ ਟੈਪ ਕਰਨ ਤੋਂ ਬਾਅਦ, ਅਸੀਂ ਤੁਹਾਡੇ ਵੱਲੋਂ ਇਕ ਈਮੇਲ ਜਾਰੀ ਕਰਾਂਗੇ।ਤੁਸੀਂ ਇਸ ਈਮੇਲ ਵਿੱਚ ਹੋਰ ਵੇਰਵੇ ਅਤੇ /ਜਾਂ ਫਾਈਲਾਂ ਨੂੰ ਇੱਥੇ ਜੋੜ ਸਕਦੇ ਹੋ।","typeHere":"ਇੱਥੇ ਟਾਈਪ ਕਰੋ ...","yesMsg":"ਹਾਂ"}}