{
  "annotations": {
    "list": [
      {
        "builtIn": 1,
        "datasource": "-- Grafana --",
        "enable": true,
        "hide": true,
        "iconColor": "rgba(0, 211, 255, 1)",
        "name": "Annotations & Alerts",
        "type": "dashboard"
      }
    ]
  },
  "editable": true,
  "gnetId": null,
  "graphTooltip": 0,
  "id": 54,
  "iteration": 1594797404526,
  "links": [],
  "panels": [
    {
      "collapsed": true,
      "datasource": null,
      "gridPos": {
        "h": 1,
        "w": 24,
        "x": 0,
        "y": 0
      },
      "id": 7,
      "panels": [
        {
          "aliasColors": {},
          "bars": false,
          "cacheTimeout": null,
          "dashLength": 10,
          "dashes": false,
          "datasource": "prom-fed",
          "fieldConfig": {
            "defaults": {
              "custom": {
                "align": null
              },
              "mappings": [
                {
                  "id": 0,
                  "op": "=",
                  "text": "N/A",
                  "type": 1,
                  "value": "null"
                }
              ],
              "nullValueMode": "connected",
              "thresholds": {
                "mode": "absolute",
                "steps": [
                  {
                    "color": "green",
                    "value": null
                  }
                ]
              },
              "unit": "none"
            },
            "overrides": []
          },
          "fill": 1,
          "fillGradient": 0,
          "gridPos": {
            "h": 7,
            "w": 12,
            "x": 0,
            "y": 1
          },
          "hiddenSeries": false,
          "id": 2,
          "legend": {
            "alignAsTable": true,
            "avg": true,
            "current": true,
            "hideEmpty": true,
            "hideZero": true,
            "max": true,
            "min": false,
            "rightSide": true,
            "show": true,
            "total": false,
            "values": true
          },
          "lines": true,
          "linewidth": 1,
          "links": [],
          "maxPerRow": 2,
          "nullPointMode": "null as zero",
          "options": {
            "dataLinks": []
          },
          "percentage": false,
          "pluginVersion": "7.0.6",
          "pointradius": 2,
          "points": false,
          "renderer": "flot",
          "repeat": "requestSize",
          "repeatDirection": "h",
          "scopedVars": {
            "requestSize": {
              "selected": false,
              "text": "1",
              "value": "1"
            }
          },
          "seriesOverrides": [],
          "spaceLength": 10,
          "stack": false,
          "steppedLine": false,
          "targets": [
            {
              "expr": "sum(increase(kong_request_size_bucket{sb_cluster=\"$cluster\", api=~\"${api}\", le=~\"$requestSize\"}[1m])) by (api,sb_cluster)",
              "hide": false,
              "interval": "",
              "intervalFactor": 1,
              "legendFormat": "{{api}}-{{sb_cluster}}",
              "refId": "A"
            },
            {
              "expr": "sum(increase(kong_request_size_bucket{sb_cluster=~\"$cluster\", sb_cluster!=\"$cluster\", api=~\"${api}\", le=~\"$requestSize\"}[1m])) by (api)",
              "hide": false,
              "interval": "",
              "intervalFactor": 1,
              "legendFormat": "{{api}}",
              "refId": "B"
            }
          ],
          "thresholds": [],
          "timeFrom": null,
          "timeRegions": [],
          "timeShift": null,
          "title": "Number of Requests under Size $requestSize kB",
          "tooltip": {
            "shared": true,
            "sort": 2,
            "value_type": "individual"
          },
          "type": "graph",
          "xaxis": {
            "buckets": null,
            "mode": "time",
            "name": null,
            "show": true,
            "values": []
          },
          "yaxes": [
            {
              "format": "short",
              "label": null,
              "logBase": 1,
              "max": null,
              "min": null,
              "show": true
            },
            {
              "format": "short",
              "label": null,
              "logBase": 1,
              "max": null,
              "min": null,
              "show": true
            }
          ],
          "yaxis": {
            "align": false,
            "alignLevel": null
          }
        }
      ],
      "repeat": null,
      "title": "Requests",
      "type": "row"
    },
    {
      "collapsed": true,
      "datasource": null,
      "gridPos": {
        "h": 1,
        "w": 24,
        "x": 0,
        "y": 1
      },
      "id": 5,
      "panels": [
        {
          "aliasColors": {},
          "bars": false,
          "cacheTimeout": null,
          "dashLength": 10,
          "dashes": false,
          "datasource": "prom-fed",
          "fieldConfig": {
            "defaults": {
              "custom": {},
              "mappings": [
                {
                  "id": 0,
                  "op": "=",
                  "text": "N/A",
                  "type": 1,
                  "value": "null"
                }
              ],
              "nullValueMode": "connected",
              "thresholds": {
                "mode": "absolute",
                "steps": [
                  {
                    "color": "green",
                    "value": null
                  }
                ]
              },
              "unit": "none"
            },
            "overrides": []
          },
          "fill": 1,
          "fillGradient": 0,
          "gridPos": {
            "h": 7,
            "w": 24,
            "x": 0,
            "y": 2
          },
          "hiddenSeries": false,
          "id": 3,
          "legend": {
            "alignAsTable": true,
            "avg": true,
            "current": true,
            "hideEmpty": true,
            "hideZero": true,
            "max": true,
            "min": false,
            "rightSide": true,
            "show": true,
            "total": false,
            "values": true
          },
          "lines": true,
          "linewidth": 1,
          "links": [],
          "maxPerRow": 2,
          "nullPointMode": "null as zero",
          "options": {
            "dataLinks": []
          },
          "percentage": false,
          "pluginVersion": "7.0.6",
          "pointradius": 2,
          "points": false,
          "renderer": "flot",
          "repeat": "responseSize",
          "repeatDirection": "h",
          "scopedVars": {
            "responseSize": {
              "selected": true,
              "text": "1",
              "value": "1"
            }
          },
          "seriesOverrides": [],
          "spaceLength": 10,
          "stack": false,
          "steppedLine": false,
          "targets": [
            {
              "expr": "sum(increase(kong_response_size_bucket{sb_cluster=\"$cluster\", api=~\"${api}\", le=~\"$responseSize\"}[1m])) by (api,sb_cluster)",
              "interval": "",
              "intervalFactor": 1,
              "legendFormat": "{{api}}-{{sb_cluster}}",
              "refId": "A"
            },
            {
              "expr": "sum(increase(kong_response_size_bucket{sb_cluster=~\"$cluster\", sb_cluster!=\"$cluster\", api=~\"${api}\", le=~\"$responseSize\"}[1m])) by (api)",
              "interval": "",
              "intervalFactor": 1,
              "legendFormat": "{{api}}",
              "refId": "B"
            }
          ],
          "thresholds": [],
          "timeFrom": null,
          "timeRegions": [],
          "timeShift": null,
          "title": "Number of Responses under Size $responseSize kB",
          "tooltip": {
            "shared": true,
            "sort": 2,
            "value_type": "individual"
          },
          "type": "graph",
          "xaxis": {
            "buckets": null,
            "mode": "time",
            "name": null,
            "show": true,
            "values": []
          },
          "yaxes": [
            {
              "format": "short",
              "label": null,
              "logBase": 1,
              "max": null,
              "min": null,
              "show": true
            },
            {
              "format": "short",
              "label": null,
              "logBase": 1,
              "max": null,
              "min": null,
              "show": true
            }
          ],
          "yaxis": {
            "align": false,
            "alignLevel": null
          }
        }
      ],
      "repeat": null,
      "title": "Responses",
      "type": "row"
    },
    {
      "collapsed": true,
      "datasource": null,
      "gridPos": {
        "h": 1,
        "w": 24,
        "x": 0,
        "y": 2
      },
      "id": 151,
      "panels": [
        {
          "cards": {
            "cardPadding": null,
            "cardRound": null
          },
          "color": {
            "cardColor": "#37872D",
            "colorScale": "linear",
            "colorScheme": "interpolateRdYlGn",
            "exponent": 0.5,
            "mode": "opacity"
          },
          "dataFormat": "tsbuckets",
          "datasource": "prom-fed",
          "fieldConfig": {
            "defaults": {
              "custom": {
                "align": null
              },
              "mappings": [],
              "thresholds": {
                "mode": "absolute",
                "steps": [
                  {
                    "color": "green",
                    "value": null
                  },
                  {
                    "color": "red",
                    "value": 80
                  }
                ]
              }
            },
            "overrides": []
          },
          "gridPos": {
            "h": 8,
            "w": 12,
            "x": 0,
            "y": 3
          },
          "heatmap": {},
          "hideZeroBuckets": true,
          "highlightCards": true,
          "id": 149,
          "legend": {
            "show": true
          },
          "maxDataPoints": 25,
          "maxPerRow": 2,
          "pluginVersion": "7.0.6",
          "repeat": "api",
          "repeatDirection": "h",
          "reverseYBuckets": false,
          "scopedVars": {
            "api": {
              "selected": false,
              "text": "assemblePage",
              "value": "assemblePage"
            }
          },
          "targets": [
            {
              "expr": "sum(increase(kong_request_size_bucket{sb_cluster=\"$cluster\", api = \"$api\"}[1m])) by (le,api,sb_cluster)",
              "interval": "",
              "intervalFactor": 1,
              "legendFormat": "{{le}}-{{sb_cluster}}",
              "refId": "A"
            },
            {
              "expr": "sum(increase(kong_request_size_bucket{sb_cluster=~\"$cluster\", sb_cluster!=\"$cluster\", api = \"$api\"}[1m])) by (le,api)",
              "interval": "",
              "intervalFactor": 1,
              "legendFormat": "{{le}}",
              "refId": "B"
            }
          ],
          "timeFrom": null,
          "timeShift": null,
          "title": "Request Heat Map of all Buckets - $api ($cluster)",
          "tooltip": {
            "show": true,
            "showHistogram": false
          },
          "type": "heatmap",
          "xAxis": {
            "show": true
          },
          "xBucketNumber": null,
          "xBucketSize": null,
          "yAxis": {
            "decimals": null,
            "format": "short",
            "logBase": 1,
            "max": null,
            "min": null,
            "show": true,
            "splitFactor": null
          },
          "yBucketBound": "middle",
          "yBucketNumber": null,
          "yBucketSize": null
        }
      ],
      "title": "Heat Map - Request",
      "type": "row"
    },
    {
      "collapsed": true,
      "datasource": null,
      "gridPos": {
        "h": 1,
        "w": 24,
        "x": 0,
        "y": 3
      },
      "id": 52,
      "panels": [
        {
          "cards": {
            "cardPadding": null,
            "cardRound": null
          },
          "color": {
            "cardColor": "#E0B400",
            "colorScale": "linear",
            "colorScheme": "interpolateRdYlGn",
            "exponent": 0.5,
            "mode": "opacity"
          },
          "dataFormat": "tsbuckets",
          "datasource": "prom-fed",
          "fieldConfig": {
            "defaults": {
              "custom": {
                "align": null
              },
              "mappings": [],
              "thresholds": {
                "mode": "absolute",
                "steps": [
                  {
                    "color": "green",
                    "value": null
                  },
                  {
                    "color": "red",
                    "value": 80
                  }
                ]
              }
            },
            "overrides": []
          },
          "gridPos": {
            "h": 8,
            "w": 12,
            "x": 0,
            "y": 4
          },
          "heatmap": {},
          "hideZeroBuckets": true,
          "highlightCards": true,
          "id": 50,
          "legend": {
            "show": true
          },
          "maxDataPoints": 25,
          "maxPerRow": 2,
          "pluginVersion": "7.0.6",
          "repeat": "api",
          "repeatDirection": "h",
          "reverseYBuckets": false,
          "scopedVars": {
            "api": {
              "selected": false,
              "text": "assemblePage",
              "value": "assemblePage"
            }
          },
          "targets": [
            {
              "expr": "sum(increase(kong_response_size_bucket{sb_cluster=\"$cluster\", api = \"$api\"}[1m])) by (le,api,sb_cluster)",
              "interval": "",
              "intervalFactor": 1,
              "legendFormat": "{{le}}",
              "refId": "A"
            },
            {
              "expr": "sum(increase(kong_response_size_bucket{sb_cluster=~\"$cluster\", sb_cluster!=\"$cluster\", api=~\"${api}\"}[1m])) by (le,api)",
              "interval": "",
              "intervalFactor": 1,
              "legendFormat": "{{le}}",
              "refId": "B"
            }
          ],
          "timeFrom": null,
          "timeShift": null,
          "title": "Response Heat Map of all Buckets - $api ($cluster)",
          "tooltip": {
            "show": true,
            "showHistogram": false
          },
          "type": "heatmap",
          "xAxis": {
            "show": true
          },
          "xBucketNumber": null,
          "xBucketSize": null,
          "yAxis": {
            "decimals": null,
            "format": "short",
            "logBase": 1,
            "max": null,
            "min": null,
            "show": true,
            "splitFactor": null
          },
          "yBucketBound": "middle",
          "yBucketNumber": null,
          "yBucketSize": null
        }
      ],
      "repeat": null,
      "title": "Heat Map - Response",
      "type": "row"
    }
  ],
  "refresh": "30s",
  "schemaVersion": 25,
  "style": "dark",
  "tags": [],
  "templating": {
    "list": [
      {
        "allValue": null,
        "current": {
          "selected": false,
          "text": "All",
          "value": "$__all"
        },
        "datasource": "prom-fed",
        "definition": "label_values(kong_request_count, sb_cluster)",
        "hide": 0,
        "includeAll": true,
        "label": null,
        "multi": false,
        "name": "cluster",
        "options": [
          {
            "selected": true,
            "text": "All",
            "value": "$__all"
          },
          {
            "selected": false,
            "text": "Kubernetes-1",
            "value": "Kubernetes-1"
          },
          {
            "selected": false,
            "text": "Kubernetes-2",
            "value": "Kubernetes-2"
          }
        ],
        "query": "label_values(kong_request_count, sb_cluster)",
        "refresh": 0,
        "regex": "",
        "skipUrlSync": false,
        "sort": 0,
        "tagValuesQuery": "",
        "tags": [],
        "tagsQuery": "",
        "type": "query",
        "useTags": false
      },
      {
        "allValue": null,
        "current": {
          "selected": false,
          "text": "All",
          "value": "$__all"
        },
        "datasource": "$cluster",
        "definition": "label_values(kong_request_count,api)",
        "hide": 0,
        "includeAll": true,
        "label": null,
        "multi": true,
        "name": "api",
        "options": [],
        "query": "label_values(kong_request_count,api)",
        "refresh": 2,
        "regex": "",
        "skipUrlSync": false,
        "sort": 0,
        "tagValuesQuery": "",
        "tags": [],
        "tagsQuery": "",
        "type": "query",
        "useTags": false
      },
      {
        "allValue": null,
        "current": {
          "selected": true,
          "text": "All",
          "value": [
            "$__all"
          ]
        },
        "datasource": "$cluster",
        "definition": "label_values(kong_request_size_bucket,le)",
        "hide": 0,
        "includeAll": true,
        "label": "Request size in kB",
        "multi": true,
        "name": "requestSize",
        "options": [],
        "query": "label_values(kong_request_size_bucket,le)",
        "refresh": 1,
        "regex": "/.*[0-9].*/",
        "skipUrlSync": false,
        "sort": 3,
        "tagValuesQuery": "",
        "tags": [],
        "tagsQuery": "",
        "type": "query",
        "useTags": false
      },
      {
        "allValue": null,
        "current": {
          "selected": true,
          "tags": [],
          "text": "",
          "value": []
        },
        "datasource": "$cluster",
        "definition": "label_values(kong_response_size_bucket,le)",
        "hide": 0,
        "includeAll": true,
        "label": "Response size in kB",
        "multi": true,
        "name": "responseSize",
        "options": [],
        "query": "label_values(kong_response_size_bucket,le)",
        "refresh": 1,
        "regex": "/.*[0-9].*/",
        "skipUrlSync": false,
        "sort": 3,
        "tagValuesQuery": "",
        "tags": [],
        "tagsQuery": "",
        "type": "query",
        "useTags": false
      }
    ]
  },
  "time": {
    "from": "now-30m",
    "to": "now"
  },
  "timepicker": {
    "refresh_intervals": [
      "10s",
      "30s",
      "1m",
      "5m",
      "15m",
      "30m",
      "1h",
      "2h",
      "1d"
    ]
  },
  "timezone": "",
  "title": "API Manager Request/Response Size Aggregated",
  "uid": "CS1kzvnMk",
  "version": 1
}
